dictionary/__init__.py
dictionary/dictionary.py
bulut_cicd_test-2.0.3.dist-info/METADATA
bulut_cicd_test-2.0.3.dist-info/WHEEL
bulut_cicd_test-2.0.3.dist-info/top_level.txt
bulut_cicd_test-2.0.3.dist-info/RECORD
