Metadata-Version: 2.1
Name: bulut-cicd-test
Version: 2.0.3
Summary: UNKNOWN
Author: Bulut Gözübüyük
License: UNKNOWN
Platform: UNKNOWN
Requires-Python: >=3.8
Requires-Dist: requests (>=2.23.0)
